{
	"title": "Where the grain goes",
	"basemap": "us-states",
	"excludeRegions": ["Alaska", "Hawaii", "Puerto Rico"],
	"unit": "million tonnes",

	"colors": {
		"line": "#141414",
		"trunk": "#c0392b",
		"callout": "#c0392b",
		"text": "#1a1a1a",
		"mapFill": "#e7e7ee",
		"mapStroke": "#ffffff",
		"background": "#fbfbfd"
	},

	"hub": { "label": "Gulf export", "region": "Louisiana" },

	"flows": [
		{ "label": "Iowa", "region": "Iowa", "value": 45 },
		{ "label": "Illinois", "region": "Illinois", "value": 30 },
		{ "label": "Nebraska", "region": "Nebraska", "value": 25 }
	],

	"callout": "Width of each line is that\nstate’s share of grain exports.",

	"steps": [
		"Three states grow most of the grain that leaves through the Gulf. Here they are as a simple chart — each bar as wide as that state’s share.",
		"Now watch where that grain actually comes from. The bars lift off and settle onto the map, at each state’s place.",
		"The routes converge and pour south, merging into a single trunk bound for the export terminals on the Gulf coast.",
		"The width never lies: the trunk is exactly as thick as the three tributaries combined."
	]
}
